flet_navigator/__init__.py
flet_navigator-3.10.11.dist-info/licenses/LICENSE
flet_navigator-3.10.11.dist-info/METADATA
flet_navigator-3.10.11.dist-info/WHEEL
flet_navigator-3.10.11.dist-info/top_level.txt
flet_navigator-3.10.11.dist-info/RECORD
