Metadata-Version: 2.4
Name: flet_navigator
Version: 3.10.11
Summary: ⚡⚓ Minimalist, fast, and effective navigation/routing library for Flet applications.
Home-page: https://github.com/xzripper/flet_navigator
Download-URL: https://github.com/xzripper/flet_navigator/archive/refs/tags/v3.10.11.tar.gz
Author: Evan
License: MIT
Classifier: License :: OSI Approved :: MIT License
Classifier: Programming Language :: Python :: 3
Classifier: Operating System :: OS Independent
Classifier: Intended Audience :: Developers
Classifier: Development Status :: 6 - Mature
Requires-Python: >=3.9
License-File: LICENSE
Dynamic: author
Dynamic: classifier
Dynamic: description
Dynamic: description-content-type
Dynamic: download-url
Dynamic: home-page
Dynamic: license
Dynamic: license-file
Dynamic: requires-python
Dynamic: summary
